pytupli/__init__.py
pytupli/benchmark.py
pytupli/cli.py
pytupli/dataset.py
pytupli/schema.py
pytupli/server/__init__.py
pytupli/server/api/__init__.py
pytupli/server/api/dependencies.py
pytupli/server/api/endpoints/__init__.py
pytupli/server/api/endpoints/artifacts.py
pytupli/server/api/endpoints/benchmarks.py
pytupli/server/api/endpoints/episodes.py
pytupli/server/api/endpoints/groups.py
pytupli/server/api/endpoints/roles.py
pytupli/server/api/endpoints/users.py
pytupli/server/api/routes.py
pytupli/server/config.py
pytupli/server/db/__init__.py
pytupli/server/db/db_handler.py
pytupli/server/env.template
pytupli/server/main.py
pytupli/server/management/__init__.py
pytupli/server/management/authorization.py
pytupli/server/management/roles.py
pytupli/storage.py
pytupli-1.2.5.dist-info/METADATA
pytupli-1.2.5.dist-info/WHEEL
pytupli-1.2.5.dist-info/entry_points.txt
pytupli-1.2.5.dist-info/licenses/LICENSE
pytupli-1.2.5.dist-info/RECORD
