Metadata-Version: 2.4
Name: pytupli
Version: 1.2.5
Summary: A package for storing and managing tuples for offline reinforcement learning.
License: MIT
License-File: LICENSE
Author: Michael Eichelbeck
Author-email: michael.eichelbeck@tum.de
Requires-Python: >=3.11,<4.0
Classifier: License :: OSI Approved :: MIT License
Classifier: Operating System :: OS Independent
Classifier: Programming Language :: Python :: 3
Classifier: Programming Language :: Python :: 3.11
Classifier: Programming Language :: Python :: 3.12
Classifier: Programming Language :: Python :: 3.13
Classifier: Programming Language :: Python :: 3.14
Requires-Dist: fire (>=0.7.0,<0.8.0)
Requires-Dist: gymnasium (>=1.1.1,<2.0.0)
Requires-Dist: jsonpickle (>=4.0.2,<5.0.0)
Requires-Dist: keyring (>=25.6.0,<26.0.0)
Requires-Dist: pandas (>=2.2.3,<3.0.0)
Requires-Dist: pydantic (>=2.10.6,<3.0.0)
Requires-Dist: pyjwt (>=2.10.1,<3.0.0)
Requires-Dist: requests (>=2.32.3,<3.0.0)
Requires-Dist: tabulate (>=0.9.0,<0.10.0)
Project-URL: Homepage, https://gitlab.lrz.de/cps/cps-rl/pytupli
